LICENSE
MANIFEST.in
README.md
pytest.ini
requirements-docs.txt
requirements-test.txt
requirements.txt
setup.py
tox.ini
steenzout/__init__.py
steenzout.sphinx.egg-info/PKG-INFO
steenzout.sphinx.egg-info/SOURCES.txt
steenzout.sphinx.egg-info/dependency_links.txt
steenzout.sphinx.egg-info/entry_points.txt
steenzout.sphinx.egg-info/namespace_packages.txt
steenzout.sphinx.egg-info/requires.txt
steenzout.sphinx.egg-info/top_level.txt
steenzout/sphinx/__init__.py
steenzout/sphinx/cli.py
steenzout/sphinx/metadata.py
steenzout/sphinx/templates/Makefile.j2
steenzout/sphinx/templates/conf.py.j2
tests/__init__.py
tests/cli_test.py
tests/metadata_test.py
tests/sphinx_test.py
tests/resources/conf.py