Metadata-Version: 1.2
Name: steenzout.sphinx
Version: 1.0.16
Summary: Sphinx configuration for the steenzout GitHub organization.
Home-page: https://github.com/steenzout/python-sphinx/
Author: Pedro Salgado
Author-email: steenzout@ymail.com
Maintainer: Pedro Salgado
Maintainer-email: steenzout@ymail.com
License: UNKNOWN
Platform: UNKNOWN
Classifier: Development Status :: 5 - Production/Stable
Classifier: Intended Audience :: Developers
Classifier: License :: OSI Approved :: Apache Software License
Classifier: Operating System :: OS Independent
Classifier: Programming Language :: Python
Classifier: Programming Language :: Python :: 2
Classifier: Programming Language :: Python :: 2.7
Classifier: Programming Language :: Python :: 3
Classifier: Programming Language :: Python :: 3.7
Classifier: Programming Language :: Python :: 3.6
Classifier: Programming Language :: Python :: 3.5
Classifier: Programming Language :: Python :: Implementation :: CPython
Classifier: Topic :: Documentation
Classifier: Topic :: Documentation :: Sphinx
Classifier: Topic :: Software Development :: Documentation
